animepics/__init__.py
animepics/core.py
animepics-0.1.0.dist-info/METADATA
animepics-0.1.0.dist-info/WHEEL
animepics-0.1.0.dist-info/top_level.txt
animepics-0.1.0.dist-info/RECORD
