Metadata-Version: 2.4
Name: animepics
Version: 0.1.0
Summary: A fun package to fetch random anime pictures from a public API.
Author-email: Your Name <your.email@example.com>
License: MIT
Project-URL: Homepage, https://github.com/yourname/animepics
Project-URL: Bug Tracker, https://github.com/yourname/animepics/issues
Requires-Python: >=3.7
Requires-Dist: requests
